README.md
setup.py
fs_sparse.egg-info/PKG-INFO
fs_sparse.egg-info/SOURCES.txt
fs_sparse.egg-info/dependency_links.txt
fs_sparse.egg-info/requires.txt
fs_sparse.egg-info/top_level.txt
sparse/__init__.py
sparse/sparse_build.py
sparse/sparse_main.py