Metadata-Version: 1.2
Name: fs-sparse
Version: 0.1
Summary: A wrapper for sparse file detection
Home-page: UNKNOWN
Author: Feiyi Wang
Author-email: fwang2@ornl.gov
License: Apache
Platform: Linux
Classifier: Development Status :: 3 - Alpha
Classifier: Intended Audience :: Developers
Classifier: Topic :: System :: Filesystems
Classifier: License :: OSI Approved :: Apache Software License
Classifier: Programming Language :: Python :: 2.7
Requires-Python: >=2.7, <3
